target_streamduo/__init__.py
target_streamduo-0.1.0.dist-info/LICENSE
target_streamduo-0.1.0.dist-info/METADATA
target_streamduo-0.1.0.dist-info/WHEEL
target_streamduo-0.1.0.dist-info/entry_points.txt
target_streamduo-0.1.0.dist-info/top_level.txt
target_streamduo-0.1.0.dist-info/RECORD
