Metadata-Version: 2.1
Name: target-streamduo
Version: 0.1.0
Summary: Singer.io target sending data to StreamDuo platform
Home-page: https://streamduo.com
Author: StreamDuo
License: UNKNOWN
Platform: UNKNOWN
Classifier: Programming Language :: Python :: 3 :: Only
License-File: LICENSE
Requires-Dist: singer-python (==5.0.12)
Requires-Dist: streamduo (==0.0.22)
